[
  {
    "name": "gunshin47",
    "uid": "124371377134",
    "character": "dffghdfhg",
    "message": "dfhrtjtyk",
    "ip": "2403:6200:8871:1c1b:243f:2583:3805:4f46"
  },
  {
    "name": "asd",
    "uid": "asd",
    "character": "asd",
    "message": "asd",
    "ip": "171.4.251.20"
  },
  {
    "name": "d",
    "uid": "d",
    "character": "d",
    "message": "",
    "ip": "171.4.251.20"
  },
  {
    "name": "gunshin47",
    "uid": "หกด",
    "character": "กด้เกเ้",
    "message": "กดนรเ่หำะกน้ร่ฟกหยดนา่้หกาดงหาฟฏฐญนดเฟบหกยดรเนหพกดเ่า้วสหกด่เ้วสา่ดปอวสราืิ่นรกหพ่ะ้ยนดกาเงยวนืิางกวดนเ่างยนกรด่เืงวสาดก่เืงสา่อปิสา่ืงดหกเ่้งย่หดกเส้่าสหพะ่้รน่หากดเสิ่หกสดราเ่้งสห่กดเ้สงวา่หเดสงา้่สาหแอ่าิสา่หดเกสร้่หสวรดกเ่้สาื่ปดสาอ่ิืวหสดเ่้นวรสดห่เ้ยน่าหกดเยน้่นยหบรด่เ้นร่ดนเรี้",
    "ip": "2403:6200:8871:1c1b:243f:2583:3805:4f46"
  }
]